MANIFEST.in
setup.py
docs/HISTORY.txt
src/dolmen/__init__.py
src/dolmen.thumbnailer.egg-info/PKG-INFO
src/dolmen.thumbnailer.egg-info/SOURCES.txt
src/dolmen.thumbnailer.egg-info/dependency_links.txt
src/dolmen.thumbnailer.egg-info/namespace_packages.txt
src/dolmen.thumbnailer.egg-info/not-zip-safe
src/dolmen.thumbnailer.egg-info/requires.txt
src/dolmen.thumbnailer.egg-info/top_level.txt
src/dolmen/thumbnailer/README.txt
src/dolmen/thumbnailer/__init__.py
src/dolmen/thumbnailer/components.py
src/dolmen/thumbnailer/configure.zcml
src/dolmen/thumbnailer/interfaces.py
src/dolmen/thumbnailer/traversal.py
src/dolmen/thumbnailer/tests/__init__.py
src/dolmen/thumbnailer/tests/ftesting.zcml
src/dolmen/thumbnailer/tests/python.jpg
src/dolmen/thumbnailer/tests/test_package.py